cchardet/__init__.py
cchardet/_cchardet.cp312-win_amd64.pyd
cchardet/version.py
faust_cchardet-2.1.19.data/scripts/cchardetect
faust_cchardet-2.1.19.dist-info/COPYING
faust_cchardet-2.1.19.dist-info/METADATA
faust_cchardet-2.1.19.dist-info/WHEEL
faust_cchardet-2.1.19.dist-info/top_level.txt
faust_cchardet-2.1.19.dist-info/RECORD
